rayvision_blender/__init__.py
rayvision_blender/analyze_blender.py
rayvision_blender/constants.py
rayvision_blender/utils.py
rayvision_blender/tests/__init__.py
rayvision_blender/tests/conftest.py
rayvision_blender/tests/test_analyse.py
rayvision_blender/tests/test_utils.py
rayvision_blender/tool/check.py
rayvision_blender-1.0.4.dist-info/METADATA
rayvision_blender-1.0.4.dist-info/WHEEL
rayvision_blender-1.0.4.dist-info/top_level.txt
rayvision_blender-1.0.4.dist-info/RECORD
