Metadata-Version: 2.1
Name: rayvision-blender
Version: 1.0.4
Summary: A Python-based API for Using Renderbus cloud rendering service.
Home-page: https://github.com/renderbus/rayvision_blender
Author: Shenzhen Rayvision Technology Co., Ltd
Author-email: developer@rayvision.com
License: UNKNOWN
Platform: UNKNOWN
Classifier: Programming Language :: Python
Classifier: Programming Language :: Python :: 2
Classifier: Programming Language :: Python :: 3
Requires-Dist: rayvision-log (>=0.3.3)
Requires-Dist: rayvision-utils (>=1.0.1)
